dmml_contest/__init__.py
dmml_contest/contest.py
dmml_contest-0.1.2.dist-info/METADATA
dmml_contest-0.1.2.dist-info/WHEEL
dmml_contest-0.1.2.dist-info/entry_points.txt
dmml_contest-0.1.2.dist-info/RECORD
