Metadata-Version: 2.4
Name: dmml-contest
Version: 0.1.2
Summary: dmml-contest
Author-email: David Apagyi <apagyi.david@gmail.com>
Requires-Python: >=3.11
Requires-Dist: pandas>=2.3.2
Requires-Dist: requests>=2.32.5
